argus_rico/__init__.py
argus_rico/afits/__init__.py
argus_rico/afits/argus_fits.py
argus_rico/catalogs/__init__.py
argus_rico/catalogs/atlas.py
argus_rico/cli.py
argus_rico/consumer.py
argus_rico/db/__init__.py
argus_rico/db/models/__init__.py
argus_rico/db/models/climate.py
argus_rico/db/models/hardware.py
argus_rico/db/models/ts_mixin.py
argus_rico/efte/__init__.py
argus_rico/efte/db.py
argus_rico/efte/efte_runner.py
argus_rico/efte/images.py
argus_rico/efte/models/__init__.py
argus_rico/efte/models/efte_alert.py
argus_rico/efte/models/evr_image.py
argus_rico/efte/processor.py
argus_rico/efte/schemas/efte.alert.avsc
argus_rico/efte/schemas/efte.candidate.avsc
argus_rico/efte/schemas/efte.xmatch.avsc
argus_rico/efte/schemas/raw_candidate.avsc
argus_rico/efte/stream.py
argus_rico/efte/vetnet.py
argus_rico/efte/watchdog.py
argus_rico/fast_healpix/.gitignore
argus_rico/fast_healpix/__init__.py
argus_rico/fast_healpix/fast_healpix.py
argus_rico/fast_healpix/fast_healpix_c.c
argus_rico/fast_healpix/fast_healpix_c_code.c
argus_rico/heartbeat.py
argus_rico/producer.py
argus_rico/py.typed
argus_rico/s3.py
argus_rico/segments.py
argus_rico/slack.py
argus_rico/slack_app.py
argus_rico/utils.py
argus_rico-0.3.4.dist-info/LICENSE
argus_rico-0.3.4.dist-info/METADATA
argus_rico-0.3.4.dist-info/WHEEL
argus_rico-0.3.4.dist-info/entry_points.txt
argus_rico-0.3.4.dist-info/RECORD
