Metadata-Version: 2.1
Name: argus-rico
Version: 0.3.4
Summary: Transient alert generation and database interaction for Argus and Evryscope
Author: Hank Corbett
Requires-Python: >=3.9
Classifier: Programming Language :: Python :: 3
Classifier: Programming Language :: Python :: 3.9
Classifier: Programming Language :: Python :: 3.10
Classifier: Programming Language :: Python :: 3.11
Classifier: Programming Language :: Python :: 3.12
Provides-Extra: dbadmin
Provides-Extra: tf
Requires-Dist: alembic (>=1.13.1) ; extra == "dbadmin"
Requires-Dist: alembic-utils (>=0.8.2) ; extra == "dbadmin"
Requires-Dist: astropy (>=5.3)
Requires-Dist: astropy-healpix (>=0.7)
Requires-Dist: blosc (>=1.11.1)
Requires-Dist: boto3 (>1.28.3)
Requires-Dist: click (>=8.1.3)
Requires-Dist: confluent-kafka (>=2.1.1)
Requires-Dist: fastavro (>=1.4.12)
Requires-Dist: geojson-pydantic (>=0.6.2)
Requires-Dist: numpy (>=1.22)
Requires-Dist: orjson (>=3.8.13)
Requires-Dist: pandas (>=2.0.2)
Requires-Dist: psycopg[binary] (==3.1.9)
Requires-Dist: pyarrow (>=13.0.0)
Requires-Dist: pydantic (>=1.10.8)
Requires-Dist: pymongo (>=4.3.3)
Requires-Dist: pymongoarrow (>=1.0.0)
Requires-Dist: python-dotenv (>=0.19.0)
Requires-Dist: ray (>=2.5.1)
Requires-Dist: sanitize-filename (>=1.2.0)
Requires-Dist: scikit-image (>=0.21.0)
Requires-Dist: slack-bolt (>=1.18.0)
Requires-Dist: sqlalchemy (>=2.0.28,<3.0.0)
Requires-Dist: tensorflow (>=2.13.0) ; extra == "tf"
Requires-Dist: watchdog (>=3.0.0)
